{
    "1119509017996296312": {
        "WarningCount": 6,
        "1": {
            "Reason": null,
            "Staff Responsible": "kaiii4222",
            "Time": "2023-10-08 15:27:38.329303"
        },
        "2": {
            "Reason": null,
            "Staff Responsible": "kaiii4222",
            "Time": "2023-10-08 15:33:05.121804"
        },
        "3": {
            "Reason": null,
            "Staff Responsible": "kaiii4222",
            "Time": "2023-10-08 15:33:17.414298"
        },
        "4": {
            "Reason": null,
            "Staff Responsible": "kaiii4222",
            "Time": "2023-10-08 15:33:23.011227"
        },
        "5": {
            "Reason": null,
            "Staff Responsible": "kaiii4222",
            "Time": "2023-10-08 15:33:40.080844"
        },
        "6": {
            "Reason": null,
            "Staff Responsible": "kaiii4222",
            "Time": "2023-10-08 15:42:43.412238"
        }
    }
}